huffc.py
py_huffc-0.1.1.dist-info/LICENSE
py_huffc-0.1.1.dist-info/METADATA
py_huffc-0.1.1.dist-info/WHEEL
py_huffc-0.1.1.dist-info/top_level.txt
py_huffc-0.1.1.dist-info/RECORD
