Metadata-Version: 2.1
Name: py-huffc
Version: 0.1.1
Summary: Python wrapper and version manager for the Huff compiler
Author: 0xcefa1090d
License: MIT License
Project-URL: Homepage, https://github.com/0xcefa1090d/py-huffc
Requires-Python: >=3.10
Provides-Extra: dev
License-File: LICENSE
